ai_clients/__init__.py
ai_clients/gemini_client.py
ai_clients/openai_client.py
unityAI/__init__.py
unityAI/unityAI.py
unityAI-0.0.2.dist-info/METADATA
unityAI-0.0.2.dist-info/WHEEL
unityAI-0.0.2.dist-info/top_level.txt
unityAI-0.0.2.dist-info/RECORD
